esanpy/__init__.py
esanpy/analyzers.py
esanpy/core.py
esanpy/elasticsearch.py
esanpy-1.1.0.dist-info/DESCRIPTION.rst
esanpy-1.1.0.dist-info/METADATA
esanpy-1.1.0.dist-info/RECORD
esanpy-1.1.0.dist-info/WHEEL
esanpy-1.1.0.dist-info/entry_points.txt
esanpy-1.1.0.dist-info/metadata.json
esanpy-1.1.0.dist-info/top_level.txt
