Metadata-Version: 2.0
Name: esanpy
Version: 1.1.0
Summary: Elasticsearch based Text Analyzer.
Home-page: https://github.com/codelibs/esanpy
Author: CodeLibs
Author-email: dev@codelibs.org
License: Apache Software License
Download-URL: https://github.com/codelibs/esanpy/tarball/1.1.0
Keywords: text analyzer
Platform: UNKNOWN
Classifier: Programming Language :: Python :: 2.7
Classifier: Programming Language :: Python :: 3
Classifier: Development Status :: 5 - Production/Stable
Classifier: Topic :: Utilities
Classifier: License :: OSI Approved :: Apache Software License
